StemLemPipe/__init__.py
StemLemPipe/metrics.py
StemLemPipe/pipeline.py
StemLemPipe/regular_expressions.py
StemLemPipe/simplifiers.py
StemLemPipe/stemlem_operators.py
StemLemPipe/stopwords.py
StemLemPipe/tokenizers.py
StemLemPipe/transformers.py
StemLemPipe/useful_functions.py
StemLemPipe-0.1.5.dist-info/LICENSE
StemLemPipe-0.1.5.dist-info/METADATA
StemLemPipe-0.1.5.dist-info/WHEEL
StemLemPipe-0.1.5.dist-info/top_level.txt
StemLemPipe-0.1.5.dist-info/RECORD
