Metadata-Version: 2.1
Name: StemLemPipe
Version: 0.1.5
Summary: simple text transformer used several stemming and lemmatization backends
Home-page: https://github.com/PasaOpasen/Stem-Lem-Pipeline
Author: Demetry Pascal
Author-email: qtckpuhdsa@gmail.com
Maintainer: ['Demetry Pascal']
License: UNKNOWN
Keywords: text,nlp,nltk,ngrams,transformation,words,stemming,lemmatization
Platform: UNKNOWN
Classifier: Programming Language :: Python :: 3
Classifier: License :: OSI Approved :: MIT License
Classifier: Operating System :: OS Independent
Classifier: Topic :: Software Development :: Libraries :: Python Modules
Requires-Dist: nltk
Requires-Dist: pymorphy2
Requires-Dist: pymystem3
Requires-Dist: stop-words
Requires-Dist: tqdm
